medisearch_client/__init__.py
medisearch_client/client.py
medisearch_client/test_client.py
medisearch_client-0.3.20.dist-info/METADATA
medisearch_client-0.3.20.dist-info/WHEEL
medisearch_client-0.3.20.dist-info/top_level.txt
medisearch_client-0.3.20.dist-info/RECORD
