Metadata-Version: 2.4
Name: medisearch_client
Version: 0.3.20
Summary: A Python client for the MediSearch medical information API
Home-page: https://github.com/MediSearch/medisearch_client_python
Author: Michal Pandy
Author-email: founders@medisearch.io
Project-URL: Documentation, https://docs.medisearch.io
Project-URL: Source, https://github.com/MediSearch/medisearch_client_python
Project-URL: Issues, https://github.com/MediSearch/medisearch_client_python/issues
Keywords: medical,healthcare,api,search,research,medisearch
Classifier: Development Status :: 4 - Beta
Classifier: Intended Audience :: Healthcare Industry
Classifier: Intended Audience :: Developers
Classifier: License :: OSI Approved :: MIT License
Classifier: Operating System :: OS Independent
Classifier: Programming Language :: Python :: 3
Classifier: Programming Language :: Python :: 3.10
Classifier: Programming Language :: Python :: 3.11
Classifier: Programming Language :: Python :: 3.12
Classifier: Programming Language :: Python :: 3.13
Classifier: Programming Language :: Python :: 3.14
Classifier: Programming Language :: Python :: 3.15
Classifier: Topic :: Scientific/Engineering :: Medical Science Apps.
Classifier: Topic :: Software Development :: Libraries :: Python Modules
Requires-Python: >=3.10
Requires-Dist: requests>=2.31.0
Requires-Dist: aiohttp>=3.9.0
Requires-Dist: rich>=13.0.0
Requires-Dist: urllib3>=2.0.0
Provides-Extra: test
Requires-Dist: rich>=13.0.0; extra == "test"
Requires-Dist: pytest>=8.0.0; extra == "test"
Requires-Dist: pytest-asyncio>=0.23.0; extra == "test"
Requires-Dist: pytest-timeout>=2.2.0; extra == "test"
Provides-Extra: dev
Requires-Dist: black>=24.0.0; extra == "dev"
Requires-Dist: isort>=5.13.0; extra == "dev"
Requires-Dist: mypy>=1.8.0; extra == "dev"
Requires-Dist: pylint>=3.0.0; extra == "dev"
Requires-Dist: ruff>=0.2.0; extra == "dev"
Dynamic: author
Dynamic: author-email
Dynamic: classifier
Dynamic: description
Dynamic: description-content-type
Dynamic: home-page
Dynamic: keywords
Dynamic: project-url
Dynamic: provides-extra
Dynamic: requires-dist
Dynamic: requires-python
Dynamic: summary
